pytheas/__about__.py
pytheas/__init__.py
pytheas/banddiag/__init__.py
pytheas/banddiag/per2D/__init__.py
pytheas/banddiag/per2D/femmodel.py
pytheas/banddiag/per2D/base/bg_mesh.geo
pytheas/banddiag/per2D/base/geometry.geo
pytheas/banddiag/per2D/base/main.pro
pytheas/basefem/__init__.py
pytheas/basefem/basefem.py
pytheas/homogenization/__init__.py
pytheas/homogenization/mixing.py
pytheas/homogenization/hctwoscale2D/__init__.py
pytheas/homogenization/hctwoscale2D/femmodel.py
pytheas/homogenization/hctwoscale2D/base/bg_mesh.geo
pytheas/homogenization/hctwoscale2D/base/geometry.geo
pytheas/homogenization/hctwoscale2D/base/main.pro
pytheas/homogenization/twoscale2D/__init__.py
pytheas/homogenization/twoscale2D/femmodel.py
pytheas/homogenization/twoscale2D/base/bg_mesh.geo
pytheas/homogenization/twoscale2D/base/geometry.geo
pytheas/homogenization/twoscale2D/base/main.pro
pytheas/homogenization/twoscale3D/__init__.py
pytheas/homogenization/twoscale3D/femmodel.py
pytheas/homogenization/twoscale3D/base/bg_mesh.geo
pytheas/homogenization/twoscale3D/base/geometry.geo
pytheas/homogenization/twoscale3D/base/main.pro
pytheas/material/__init__.py
pytheas/material/genmat.py
pytheas/material/refractiveindex.py
pytheas/optim/__init__.py
pytheas/optim/topopt.py
pytheas/optim/topopt3d.py
pytheas/periodic2D/__init__.py
pytheas/periodic2D/femmodel.py
pytheas/periodic2D/base/bg_mesh.geo
pytheas/periodic2D/base/geometry.geo
pytheas/periodic2D/base/main.pro
pytheas/periodic3D/__init__.py
pytheas/periodic3D/femmodel.py
pytheas/periodic3D/base/geometry.geo
pytheas/periodic3D/base/geometry_legacy.geo
pytheas/periodic3D/base/geometry_new.geo
pytheas/periodic3D/base/geometry_new2.geo
pytheas/periodic3D/base/geometry_old.geo
pytheas/periodic3D/base/geometry_struct.geo
pytheas/periodic3D/base/main.pro
pytheas/periodic3D/base/main_new.pro
pytheas/scatt2D/__init__.py
pytheas/scatt2D/femmodel.py
pytheas/scatt2D/base/bg_mesh.geo
pytheas/scatt2D/base/geometry.geo
pytheas/scatt2D/base/main.pro
pytheas_pip-1.1.1.dist-info/LICENCE.txt
pytheas_pip-1.1.1.dist-info/METADATA
pytheas_pip-1.1.1.dist-info/WHEEL
pytheas_pip-1.1.1.dist-info/top_level.txt
pytheas_pip-1.1.1.dist-info/RECORD
