Metadata-Version: 2.1
Name: pytheas-pip
Version: 1.1.1
Summary: Python Electromagnetic Analysis and Simulation with the Finite Element Method
Home-page: https://benvial.github.io/pytheas
Author: Benjamin Vial
Author-email: benjamin.vial84@gmail.com
License: License :: OSI Approved :: MIT License
Project-URL: Documentation, https://benvial.github.io/pytheas
Platform: any
Classifier: Development Status :: 5 - Production/Stable
Classifier: License :: OSI Approved :: MIT License
Classifier: Intended Audience :: Science/Research
Classifier: Operating System :: OS Independent
Classifier: Programming Language :: Python
Classifier: Programming Language :: Python :: 3
Classifier: Topic :: Scientific/Engineering :: Mathematics
Requires-Dist: numpy
Requires-Dist: scipy
Requires-Dist: matplotlib
Requires-Dist: meshio
Requires-Dist: pygmsh
Requires-Dist: PyYAML
Requires-Dist: parse
Provides-Extra: all
Requires-Dist: pipdate (<0.4.0,>=0.3.0) ; extra == 'all'
Provides-Extra: update
Requires-Dist: pipdate (<0.4.0,>=0.3.0) ; extra == 'update'
